{"Id":"155120","ProductId":"P1000-01","UserId":"A10ZA98GVHGY9W","ProfileName":"rio","HelpfulnessNumerator":2,"HelpfulnessDenominator":2,"Score":5,"Time":"1319760000","Summary":"NUTIVA COCONUT OIL","text":"I HAVE BEEN USING THIS PRODUCT EVERY DAY ALONG WITH COD LIVER OIL FOR 7 MONTHS. DRY AND DAMAGED SKIN FROM THE SUN HEALED IN 2 MONTHS. I TRIED FOR 35 YEARS TO HEAL MY DAMAGED LEGS BUT NOTHING WORKED AND THEN THIS!!!<br /><br />IT HAS ALSO GIVEN ME A FEELING OF WELL BEING. I FEEL THAT I AM DOING SOMETHING GOOD FOR MYSELF."}