{"Id":"189537","ProductId":"P1000-04","UserId":"A3H6NNGCINPLEC","ProfileName":"A Customer","HelpfulnessNumerator":1,"HelpfulnessDenominator":1,"Score":5,"Time":"1236729600","Summary":"Nutiva Organic Coconut Oil","text":"The Nutiva Organic Coconut Oil is one of the best, bar none! We use this product for our skin, hair, and separately in the kitchen.<br /><br />We highly recommend reading:  <a href=\"http://www.amazon.com/gp/product/1583332049\">The Coconut Oil Miracle (Previously published as The Healing Miracle of Coconut Oil)</a> and other books by the author, whom has founded a Coconut Research Center."}