{"Id":"240228","ProductId":"P1000-02","UserId":"A19XBW5WUDH1Z","ProfileName":"David Nox","HelpfulnessNumerator":2,"HelpfulnessDenominator":2,"Score":4,"Time":"1342828800","Summary":"Good basic maintenance dog food","text":"I have 4 Chihuahuas and these kibbles are small enough that they have no problems eating them.<br />My dogs are picky eaters but they seem to enjoy this. The packaging is super strong with a ziplock type seal.<br />This will protect the package during shipping and keep it fresh in your house.<br />I supplement this food with canned food and home cooked food. I like to keep my dogs diet as balanced as possible."}