[{"productId":"P1000-01","name":"Product A","price":"3.99"},{"productId":"P1000-02","name":"Product B","price":"3.99"},{"productId":"P1000-03","name":"Product C","price":"3.99"},{"productId":"P1000-04","name":"Product D","price":"3.99"},{"productId":"P1000-05","name":"Product E","price":"3.99"},{"productId":"P1000-06","name":"Product F","price":"3.99"},{"productId":"P1000-07","name":"Product G","price":"3.99"},{"productId":"P1000-08","name":"Product H","price":"3.99"},{"productId":"P1000-09","name":"Product I","price":"3.99"},{"productId":"P1000-10","name":"Product J","price":"3.99"}]